pictureflow/__init__.py
pictureflow/core/__init__.py
pictureflow/core/constant.py
pictureflow/core/image.py
pictureflow/core/node.py
pictureflow/core/placeholder.py
pictureflow/core/session.py
pictureflow/flow/__init__.py
pictureflow/flow/broadcast.py
pictureflow/flow/combine.py
pictureflow/output/__init__.py
pictureflow/output/disk.py
pictureflow/transform/__init__.py
pictureflow/transform/color.py
pictureflow/transform/convert.py
pictureflow/transform/path.py
pictureflow/transform/rotate.py
pictureflow/transform/scale.py
pictureflow/vision/__init__.py
pictureflow/vision/contour_detection.py
pictureflow/vision/object_detector.py
pictureflow-1.1.1.dist-info/DESCRIPTION.rst
pictureflow-1.1.1.dist-info/METADATA
pictureflow-1.1.1.dist-info/RECORD
pictureflow-1.1.1.dist-info/WHEEL
pictureflow-1.1.1.dist-info/metadata.json
pictureflow-1.1.1.dist-info/top_level.txt
test/__init__.py
test/context.py
test/test_core/__init__.py
test/test_core/test_constant.py
test/test_core/test_image.py
test/test_core/test_node.py
test/test_core/test_placeholder.py
test/test_core/test_session.py
test/test_flow/__init__.py
test/test_flow/test_broadcast.py
test/test_flow/test_combine.py
test/test_output/__init__.py
test/test_output/test_disk.py
test/test_transform/__init__.py
test/test_transform/test_color.py
