Metadata-Version: 2.0
Name: pictureflow
Version: 1.1.1
Summary: Image processing with a tensorflow-inspired API
Home-page: https://github.com/mentum/pictureflow
Author: mentum
Author-email: dalloriam@gmail.com
License: MIT
Platform: UNKNOWN
Requires-Dist: numpy
Requires-Dist: opencv-python (==3.3.0.10)
